zconfig_watchedfile/__init__.py
zconfig_watchedfile/component.xml
zconfig_watchedfile/handler.py
zconfig_watchedfile/tests/__init__.py
zconfig_watchedfile/tests/schema.xml
zconfig_watchedfile/tests/test_handler.py
zconfig_watchedfile-2.0.dist-info/LICENSE.txt
zconfig_watchedfile-2.0.dist-info/METADATA
zconfig_watchedfile-2.0.dist-info/WHEEL
zconfig_watchedfile-2.0.dist-info/top_level.txt
zconfig_watchedfile-2.0.dist-info/RECORD
