Metadata-Version: 2.1
Name: zconfig-watchedfile
Version: 2.0
Summary: ZConfig statement to register a logging handler using WatchedFileHandler
Home-page: https://github.com/gocept/zconfig_watchedfile
Author: gocept <mail@gocept.com>
Author-email: mail@gocept.com
License: ZPL 2.1
Keywords: ZConfig WatchedFileHandler logging handler
Classifier: License :: OSI Approved :: Zope Public License
Classifier: Development Status :: 5 - Production/Stable
Classifier: Programming Language :: Python
Classifier: Programming Language :: Python :: 3.8
Classifier: Programming Language :: Python :: 3.9
Classifier: Programming Language :: Python :: 3.10
Classifier: Programming Language :: Python :: 3.11
Requires-Python: >=3.8
License-File: LICENSE.txt
Requires-Dist: ZConfig
Requires-Dist: setuptools
Provides-Extra: test
